<?xml version="1.0" encoding="utf-8"?>
<!-- This XML was generated by Rcomage v1.1.1 -->
<TextLang>
	<Text name="msgshare_opt_del">Verwijderen</Text>
	<Text name="msgshare_opt_info">Informatie</Text>
	<Text name="msgshare_connect">Verbinden</Text>
	<Text name="msgshare_opt_edit">Bewerken</Text>
	<Text name="msgshare_opt_connect_test">Verbinding testen</Text>
	<Text name="msgshare_percent">%1%%</Text>
	<Text name="msgshare_on">Aan</Text>
	<Text name="msgshare_off">Uit</Text>
	<Text name="msgshare_auto">Automatisch</Text>
	<Text name="msgshare_manual">Handmatig</Text>
	<Text name="msgshare_use">Gebruiken</Text>
	<Text name="msgshare_not_use">Niet gebruiken</Text>
	<Text name="msgshare_canceling">Bezig met annuleren...
Een ogenblik geduld.</Text>
	<Text name="msgshare_saved">Het opslaan is voltooid.</Text>
	<Text name="msgshare_deleting_notturnoff">Bezig met verwijderen...
Schakel de stroom niet uit.</Text>
	<Text name="msgshare_deleted">Het verwijderen is voltooid.</Text>
	<Text name="msgshare_error_lan_off">Er is een verbindingsfout opgetreden.
De WLAN-schakelaar op het PSP™-systeem is niet ingeschakeld.</Text>
	<Text name="msgshare_error_wireless_off">Er is een verbindingsfout opgetreden.
De WIRELESS (draadloos)-schakelaar op het PSP™-systeem is niet ingeschakeld.</Text>
	<Text name="msgshare_direction_lr">Druk de toets ◀ om terug te gaan of de toets ▶ om door te gaan.</Text>
	<Text name="msgshare_direction_r">Druk op de toets ▶ om door te gaan.</Text>
	<Text name="msgshare_direction_l">Druk op de toets ◀ om terug te gaan.</Text>
	<Text name="msgshare_error_internal">Er is een interne fout opgetreden.</Text>
	<Text name="msgshare_error_connect">Er is een verbindingsfout opgetreden.</Text>
	<Text name="msgshare_error_connect_disconnect">Er is een verbindingsfout opgetreden.
De verbinding met het netwerk is verbroken.</Text>
	<Text name="msgshare_connecting">Bezig met verbinden...
Een ogenblik geduld.</Text>
	<Text name="msgshare_wait">Een ogenblik geduld...</Text>
	<Text name="msgshare_error_notconnected">U bent niet verbonden met het netwerk.</Text>
	<Text name="msgshare_error">Er is een fout opgetreden.</Text>
	<Text name="msgshare_failed">Mislukt</Text>
	<Text name="msgshare_error_ap_disconnect">Er is een verbindingsfout opgetreden.
De verbinding met het toegangspunt is verbroken.</Text>
	<Text name="msgshare_error_pppoe_disconnect">Er is een verbindingsfout opgetreden.
De verbinding met de PPPoE-server is verbroken.</Text>
	<Text name="msgshare_error_pppoe_com">Er is een verbindingsfout opgetreden.
Er was sprake van een PPPoE-communicatiefout.</Text>
	<Text name="msgshare_channel">Kanaal</Text>
	<Text name="msgshare_error_connection_timeout">Er is een time-out opgetreden voor de verbinding met de server.</Text>
	<Text name="msgshare_error_dns">De communicatie met de server is mislukt.
Er is een DNS-fout opgetreden.</Text>
	<Text name="msgshare_address">Adres</Text>
	<Text name="msgtop_sysconf_network">Netwerkinstellingen</Text>
	<Text name="msgtop_network_browser">Internetbrowser</Text>
	<Text name="msg_psspot">PlayStation®Spot</Text>
	<Text name="msg_psspot_instruction">Er wordt automatisch een netwerkverbinding voor de internetverbinding op een PlayStation®Spot gemaakt.</Text>
	<Text name="msg_error_bt_device_over">Er kunnen niet meer Bluetooth®-apparaten worden aangesloten.
Om dit apparaat te verbinden dient u de verbinding met andere Bluetooth®-apparaten te verbreken.</Text>
	<Text name="msg_device_name">Naam apparaat</Text>
	<Text name="msgnetconf_newconnect">[Nieuwe verbinding ]</Text>
	<Text name="msgnetconf_connectname">Naam van verbinding</Text>
	<Text name="msgnetconf_connectname_default">Verbinding %1</Text>
	<Text name="msgnetconf_ssid">SSID</Text>
	<Text name="msgnetconf_none">Geen</Text>
	<Text name="msgnetconf_wep">WEP</Text>
	<Text name="msgnetconf_wepkey">WEP-sleutel</Text>
	<Text name="msgnetconf_searching">Bezig met scannen...
Een ogenblik geduld.</Text>
	<Text name="msgnetconf_signalstrength">Signaalsterkte</Text>
	<Text name="msgnetconf_error_notfound_tryagain">Er is geen toegangspunt gevonden.
Wilt u het opnieuw proberen?</Text>
	<Text name="msgnetconf_choose_ipaddress">Instelling IP-adres</Text>
	<Text name="msgnetconf_pppoe">PPPoE</Text>
	<Text name="msgnetconf_choose_dns">DNS-instelling</Text>
	<Text name="msgnetconf_ipaddress">IP-adres</Text>
	<Text name="msgnetconf_netmask">Netmasker</Text>
	<Text name="msgnetconf_defaultrooter">Standaardrouter</Text>
	<Text name="msgnetconf_primedns">Primaire DNS</Text>
	<Text name="msgnetconf_seconddns">Secundaire DNS</Text>
	<Text name="msgnetconf_userid">Gebruikersnaam</Text>
	<Text name="msgnetconf_password">Wachtwoord</Text>
	<Text name="msgnetconf_proxyserver">Proxyserver</Text>
	<Text name="msgnetconf_proxyserver_number">Poortnummer</Text>
	<Text name="msgnetconf_autoconnection">Automatisch</Text>
	<Text name="msgnetconf_bssid">BSSID</Text>
	<Text name="msgnetconf_macaddress">MAC-adres</Text>
	<Text name="msgnetconf_set">Druk op de toets %e om de instellingen op te slaan.</Text>
	<Text name="msgnetconf_cancel_setup_ask">Wilt u annuleren?
De instellingen die u tot nu toe hebt gemaakt, worden niet opgeslagen als u nu annuleert.</Text>
	<Text name="msgnetconf_del_connect_ask">Wilt u deze verbinding verwijderen?</Text>
	<Text name="msgnetconf_cmn_title_netconnect">Netwerkverbinding</Text>
	<Text name="msgnetconf_cmn_title_status">Verbindingsstatus</Text>
	<Text name="msgnetconf_cmn_go_netconf">U moet een netwerkverbinding maken om door te gaan.</Text>
	<Text name="msgnetconf_cmn_choose_connect">Verbinding selecteren.</Text>
	<Text name="msgnetconf_cmn_connecting">Bezig met verbinden met het toegangspunt...
Een ogenblik geduld.</Text>
	<Text name="msgnetconf_start_new">Maak verbinding.</Text>
	<Text name="msgnetconf_start_edit">Selecteer de verbinding die u wilt bewerken.</Text>
	<Text name="msgnetconf_enter_connectname">Voer een naam voor de verbinding in.</Text>
	<Text name="msgnetconf_enter_wlan">WLAN-instellingen</Text>
	<Text name="msgnetconf_choose_address">Adresinstellingen</Text>
	<Text name="msgnetconf_choose_address_auto">Eenvoudig</Text>
	<Text name="msgnetconf_choose_address_manual">Aangepast</Text>
	<Text name="msgnetconf_error_wep_length">De door u ingevoerde tekens zijn ongeldig.
Voor hexadecimaal:
gebruik 10 of 26 tekens uit de bereiken 0-9, a-f en A-F
Voor ASCII: gebruik 5 of 13 tekens</Text>
	<Text name="msgnetconf_error_connectname_same">De naam van een bestaande verbinding kan niet worden gebruikt.</Text>
	<Text name="msgnetconf_adhocmode">Ad hoc-modus</Text>
	<Text name="msg_adhocmode_info">Wijzigt de instellingen voor rechtstreekse communicatie tussen PSP™-systemen zonder gebruik van het internet.</Text>
	<Text name="msgnetconf_inframode">Infrastructuurmodus</Text>
	<Text name="msg_inframode_info">Wijzigt de instellingen voor verbinding met het internet.</Text>
	<Text name="msgnetconf_channel_com">Stel deze optie in op het gebruikte kanaal voor de PSP™-systemen waarmee u verbinding wilt maken.</Text>
	<Text name="msgnetconf_error_no_name">Er is geen verbindingsnaam ingevoerd.
Voer een naam van minimaal 1 teken in.</Text>
	<Text name="msgnetconf_test">Verbinding testen</Text>
	<Text name="msgnetconf_error_set_connecting">Deze bewerking kan alleen worden uitgevoerd wanneer u niet verbonden bent met het netwerk.</Text>
	<Text name="msgnetconf_error_dhcp_com">Er is een verbindingsfout opgetreden.
Er was sprake van een DHCP-communicatiefout.</Text>
	<Text name="msgnetconf_error_pppep_not_found">Er is een verbindingsfout opgetreden.
Er is geen PPPoE-server gevonden.</Text>
	<Text name="msgnetconf_error_dhcp_not_found">Er is een verbindingsfout opgetreden.
Er is geen DHCP-server gevonden.</Text>
	<Text name="msgnetconf_error_pppoe_error">Er is een verbindingsfout opgetreden.
De PPPoE-server gaf een fout als resultaat.</Text>
	<Text name="msgnetconf_error_pppoe_wrong_id_pw">Er is een verbindingsfout opgetreden.
De PPPoE-gebruikernsaam of het PPPoE-wachtwoord is onjuist.</Text>
	<Text name="msgnetconf_error_port_number">Het poortnummer is ongeldig.
Voer een getal in tussen de 1 en 65535.</Text>
	<Text name="msgnetconf_internet_connection">Internetverbinding</Text>
	<Text name="msgnetconf_succeeded">Geslaagd</Text>
	<Text name="msgnetconf_list">Instellingenlijst</Text>
	<Text name="msgnetconf_ch">Ch %1</Text>
	<Text name="msgnetconf_scan_ssid">Scannen</Text>
	<Text name="msgnetconf_enter_ssid">Handmatig invoeren</Text>
	<Text name="msgnetconf_scan_ssid_instruction">Het PSP™-systeem zal de SSID van het toegangspunt zoeken. Selecteer deze optie als u de SSID niet weet.</Text>
	<Text name="msgnetconf_enter_ssid_instruction">Voer de SSID van het toegangspunt handmatig in.</Text>
	<Text name="msgnetconf_select_ap">Selecteer het te gebruiken toegangspunt.</Text>
	<Text name="msgnetconf_wlansecurity_setting">Instelling WLAN-beveiliging</Text>
	<Text name="msgnetconf_wpapsk_tkip">WPA-PSK (TKIP)</Text>
	<Text name="msgnetconf_wpakey">WPA-sleutel</Text>
	<Text name="msgnetconf_error_wpa_length">De door u ingevoerde tekens zijn ongeldig.
Gebruik een van de volgende patronen.
Voor hexadecimaal:
gebruik 64 tekens uit de bereiken 0-9, a-f en A-F
Voor ASCII: Gebruik 8 tot 63 tekens</Text>
	<Text name="msgnetconf_authentication_setting">Verificatie-instelling</Text>
	<Text name="msgnetconf_eapmd5_kr">EAP-MD5</Text>
	<Text name="msgnetconf_eapmd5_id_kr">EAP-verificatie
gebruikersnaam</Text>
	<Text name="msgnetconf_eapmd5_password_kr">EAP-verificatie
wachtwoord</Text>
	<Text name="msgnetconf_launch_browser">Starten</Text>
	<Text name="msgnetconf_not_launch_browser">Niet starten</Text>
	<Text name="msgnetconf_select_not_launch">Doorgaans wordt deze optie geselecteerd.</Text>
	<Text name="msgnetconf_select_launch">Nadat er verbinding is met het toegangspunt wordt een internetbrowser gestart. Selecteer deze optie bij gebruik van een internetbrowser voor aanmeldingen vanaf hotspotservices.</Text>
	<Text name="msgnetconf_error_ap_timeout">Verbindingsfout.
Time-out tijdens het maken van een verbinding met het toegangspunt.</Text>
	<Text name="msgnetconf_getting_ipaddress">IP-adres wordt aangevraagd...
Een ogenblik geduld.</Text>
	<Text name="msgnetconf_error_ipaddress_timeout">Verbindingsfout.
Time-out tijdens poging om IP-adres op te halen.</Text>
	<Text name="msg_error_ipaddress_timeout_wrong_pw">Time-out tijdens poging om IP-adres op te halen.
De door u ingevoerde WEP-sleutel is mogelijk incorrect.</Text>
	<Text name="msgnetconf_error_authenticate_timeout">Verbindingsfout.
Time-out tijdens de verificatie.</Text>
	<Text name="msgnetconf_md5_authenticating">EAP-verificatie wordt uitgevoerd...
Een ogenblik geduld.</Text>
	<Text name="msgnetconf_md5_keyexchanging">Sleutelinformatie wordt uitgewisseld...
Een ogenblik geduld.</Text>
	<Text name="msg_error_keyexchange_timeout_wrong_pw">Time-out tijdens uitwisseling van sleutelinformatie.
De door u ingevoerde WPA-sleutel is mogelijk incorrect.</Text>
	<Text name="msgnetconf_testing_internet">Internet-verbinding wordt getest...
Een ogenblik geduld.</Text>
	<Text name="msgnetconf_starting_browser">Internetbrowser wordt gestart...
Een ogenblik geduld.
Nadat u zich hebt aangemeld, kunt u de internetbrowser sluiten.</Text>
	<Text name="msgnetconf_error_apsecurity_notsupported">De beveilgingsmethode van dit toegangspunt wordt niet door het PSP™-systeem ondersteund.</Text>
	<Text name="msgnetconf_pppoeid">PPPoE-gebruikersnaam</Text>
	<Text name="msgnetconf_pppoepw">PPPoE-wachtwoord</Text>
	<Text name="msgnetconf_security">Beveiliging</Text>
	<Text name="msgnetconf_info_authentication">Verificatie</Text>
	<Text name="msgnetconf_notsupported">Niet ondersteund</Text>
	<Text name="msgnetconf_apautosetting">Automatisch</Text>
	<Text name="msgnetconf_apautosetting_caption">Automatische instellingen op basis van het type toegangspunt. Selecteer deze optie wanneer u een toegangspunt gebruikt dat het automatisch instellen van het draadloze netwerk ondersteunt.</Text>
	<Text name="msg_bt_modem">Bluetooth®-Modem</Text>
	<Text name="msg_bt_modem_info">Stel deze optie in om te verbinden met het internet door gebruik te maken van een modem (mobiele telefoon) die Bluetooth® ondersteund.</Text>
	<Text name="msg_error_bt_modem_not_registered"><![CDATA[Er zijn geen Bluetooth®-modems geregistreerd.
Registreer een Bluetooth®-modem (mobiele telefoon) onder [Instellingen] > [Instellingen Bluetooth®-apparaat] > [Bluetooth®-apparaten beheren].]]></Text>
	<Text name="msg_phone_number2">Inbelnummer</Text>
	<Text name="msg_initialize_command">Startopdracht</Text>
	<Text name="msg_get_from_bt_modem">Verkrijgen van Bluetooth®-modem</Text>
	<Text name="msg_error_no_connect_information">Informatie nodig voor de verbinding kon niet worden gevonden.
U moet de informatie handmatig invoeren.</Text>
	<Text name="msg_select_bt_modem">Selecteer de te gebruiken Bluetooth®-modem.</Text>
	<Text name="msg_bt_modem_connecting">Bezig met verbinden naar de Bluetooth®-modem...
Een ogenblik geduld.</Text>
	<Text name="msg_getting_connect_information">Bezig met het verkrijgen van informatie nodig voor de verbinding...
Een ogenblik geduld.</Text>
	<Text name="msg_error_bt_device_connection_off2"><![CDATA[[Instellingen] > [Instellingen Bluetooth®-apparaat] > [Bluetooth®-verbinding] is ingesteld op [Uit].
Wilt u deze instellen op [Aan]?]]></Text>
	<Text name="msg_error_input_characters">De door u ingevoerde tekens zijn ongeldig.</Text>
	<Text name="msg_bt_modem_connection_legal_notice">Beschikbaarheid van de internetverbinding, downloadsnelheden en kosten van data-overdracht bij het gebruik van een apparaat, inclusief een mobiele telefoon, verbonden met uw PSP™-systeem via Bluetooth®, kunnen verschillen afhankelijk van de service provider voor uw verbonden apparaat. GEBRUIKERS ZIJN ZELF VERANTWOORDELIJK VOOR ALLE KOSTEN DIE AANGEREKEND WORDEN DOOR DE SERVICE PROVIDERS OF DERDE PARTIJEN. Bekijk vooraf de kosten die uw service provider in rekening brengt. Een standaard pakket kan misschien niet voorzien in de kosten van een internet verbinding bij gebruik van Bluetooth® en extra kosten kunnen in rekening worden gebracht afhankelijk van download grootte en verbindingstijd. Lees de online handleiding voor u uw verbonden apparaat gebruikt om data van het internet te downloaden naar uw PSP™-systeem.</Text>
	<Text name="msgnetconf_rakurakuwlanstart">Rakuraku WLAN Start</Text>
	<Text name="msgnetconf_aoss">AOSS™</Text>
	<Text name="msgnetconf_raku_caption">"Rakuraku WLAN Start" is a technology developed by NEC Access Technica, Inc. It is possible to make wireless LAN settings by using the "Rakuraku Start Button" of the Aterm® series. *Except for Aterm® series, a different operating might be necessary.</Text>
	<Text name="msgnetconf_aoss_caption">AOSS™ (AirStation One-Touch Secure System) is een technologie die door Buffalo, Inc. werd ontwikkeld. Hiermee is het mogelijk de instellingen van uw draadloos LAN met één druk op de knop te configureren.</Text>
	<Text name="msgnetconf_searchingforap">Preparing...
Please wait.</Text>
	<Text name="msgnetconf_raku_pushbutton1">Press and hold the "Rakuraku Start Button" of the access point until the "POWER" LED blinks in [Green].
If you don't press the button within 1 minute, the operation will be cancelled.
*Please see the manual of the product appending, about the connection method of the product without "Rakuraku Start Button".</Text>
	<Text name="msgnetconf_raku_pushbutton2">Press the "Rakuraku Start Button" again. Press and hold until the "POWER" LED turns [Orange].
If you don't press the button within 30 seconds, the operation will be cancelled.
*Please see the manual of the product appending, about the connection method of the product without "Rakuraku Start Button".</Text>
	<Text name="msgnetconf_aoss_pushbutton">Houd de "knop AOSS" van het toegangspunt ingedrukt tot de AOSS-indicator begint te knipperen.
Als u de knop niet binnen 2 minuten indrukt, wordt de bewerking geannuleerd.</Text>
	<Text name="msgnetconf_error_toomanyap">Er zijn te veel toegangspunten.
Leg de instellingen vast op een plaats waar er maar een paar toegangspunten zijn.</Text>
	<Text name="msgnetconf_error_apnotfound">Het toegangspunt is niet gevonden.</Text>
	<Text name="msg_error_ap_notfound_wrong_ssid">Het toegangspunt is niet gevonden.
Mogelijk is het signaal van het toegangspunt zwak of is de door u ingevoerde SSID incorrect.</Text>
	<Text name="msgnetconf_error_setting_timeout">Er is een time-outfout opgetreden tijdens de setup.</Text>
	<Text name="msgnetconf_error_ap_security">Verbindingsfout.
Er kon geen verbinding worden gemaakt met het toegangspunt.
Controleer de beveiligingsinstellingen van het WLAN en probeer het opnieuw.</Text>
	<Text name="msgnetconf_eap_authentication_kr">EAP-verificatie</Text>
	<Text name="msgnetconf_rakuaoss_canceling">Cancelling...
Please wait.</Text>
	<Text name="msgnetconf_rakuaoss_wait">Please wait...</Text>
	<Text name="msgnetconf_rakuaoss_error_lan_off">A connection error has occurred.
The WLAN switch on the PSP™ system is not turned on.</Text>
	<Text name="msgnetconf_rakuaoss_error_wireless_off">A connection error has occurred.
The WIRELESS switch on the PSP™ system is not turned on.</Text>
	<Text name="msgnetconf_rakuaoss_error_ap_disconnect">A connection error has occurred.
You have been disconnected from the access point.</Text>
	<Text name="msgnetconf_rakuaoss_error_apsecurity_notsupported">The PSP™ system does not support the security method of this access point.</Text>
	<Text name="msgnetconf_aoss_wait">Het duurt ongeveer 10 seconden voordat het toegangspunt klaar is.
Een ogenblik geduld...</Text>
	<Text name="msgnetconf_error_connection_timeout">Er is een verbindingsfout opgetreden.
Een time-out tijdens de verbindingspoging.</Text>
	<Text name="msgnetconf_error_wlan_assoc_timeout">Er is een verbindingsfout opgetreden.
Mogelijk is het signaal zwak.</Text>
	<Text name="msgnetconf_error_wlan_timeout">Er is een verbindingsfout opgetreden.
Probeer het opnieuw.</Text>
	<Text name="msgnetconf_wpapsk_aes">WPA-PSK (AES)</Text>
	<Text name="msg_wifi_sp">Draadloze hotspot</Text>
	<Text name="msg_set_wifi_sp_instruction">Ingesteld voor toegang tot een draadloze hotspot.</Text>
	<Text name="msg_error_user_authentication">Verificatie van gebruiker kon niet worden voltooid.
%1</Text>
	<Text name="msg_user_authenticating">Bezig met verificatie...
Een ogenblik.</Text>
	<Text name="msg_wifi_sp_userid">Draadloze hotspot gebruikers-ID</Text>
	<Text name="msg_wifi_sp_userid_info">Draadloze hotspot
Gebruikers-ID</Text>
	<Text name="msg_wifi_sp_pswd">Draadloze hotspot wachtwoord</Text>
	<Text name="msg_wifi_sp_pswd_info">Draadloze hotspot
Wachtwoord</Text>
	<Text name="msg_error_connection_same_change">Een verbinding met de naam hieronder bestaat al.
%1
 Neem een andere naam voor de verbinding.</Text>
	<Text name="msg_error_connection_same">De verbinding hieronder is al aangemaakt. U kunt er niet meer dan één hebben.
%1</Text>
	<Text name="msg_error_input_wrong_ascii_pls">De door u ingevoerde tekens zijn ongeldig. U kunt hier alleen ASCII-tekens gebruiken.</Text>
	<Text name="msg_error_invalid_number">De door u ingevoerde waarde is ongeldig.</Text>
	<Text name="msg_tmobile">T-Mobile® USA</Text>
	<Text name="msg_promotional_access">Use Promotional Access</Text>
	<Text name="msg_user_credentials">Enter User Credentials</Text>
	<Text name="msg_promotional_access_instruction">Use limited time promotional access from T-Mobile® HotSpot at thousands of convenient locations throughout the USA.</Text>
	<Text name="msg_user_credentials_instruction">Use your existing T-Mobile® HotSpot service credentials at thousands of convenient locations throughout the USA.</Text>
	<Text name="msg_tmobile_instruction">Go mobile and stay connected! Experience the blazing fast speed of T-Mobile® HotSpot Wi-Fi service at thousands of convenient locations throughout the USA.</Text>
	<Text name="msg_upnp">UPnP</Text>
	<Text name="msg_nattype">NAT-type</Text>
	<Text name="msg_type1">Type 1</Text>
	<Text name="msg_type2">Type 2</Text>
	<Text name="msg_type3">Type 3</Text>
	<Text name="msg_enabled">Ingeschakeld</Text>
	<Text name="msg_disabled">Uitgeschakeld</Text>
	<Text name="msg_nattype3_info">Wanneer het NAT-type type 3 is, kunnen de communicatiefuncties van games beperkt zijn. Raadpleeg de online handleiding voor meer informatie.</Text>
	<Text name="msg_router_no_ipfragments_info">De gebruikte router ondersteunt mogelijkerwijs geen IP-fragmentatie en voor sommige games kunnen de communicatiefuncties worden beperkt. Voor details neemt u contact op met de routerfabrikant.</Text>
	<Text name="msglftv_settings_easy_connection_delete">U kunt maximaal 10 netwerkverbindingen opslaan.
Verwijder een opgeslagen verbinding uit [Instellingen], [Netwerkinstellingen].</Text>
	<Text name="msg_not_show_message">Niet meer weergeven</Text>
	<Text name="msg_error_use_network_feature">Netwerkfuncties zijn niet beschikbaar op dit systeem.</Text>
</TextLang>
