<?xml version="1.0" encoding="utf-8"?>
<!-- This XML was generated by Rcomage v1.1.1 -->
<TextLang>
	<Text name="msgshare_opt_del">Verwijderen</Text>
	<Text name="msgshare_opt_info">Informatie</Text>
	<Text name="msgshare_info_date">Bijgewerkt</Text>
	<Text name="msgshare_info_size">Grootte</Text>
	<Text name="msgshare_info_title">Titel</Text>
	<Text name="msgshare_info_none">-</Text>
	<Text name="msgshare_info_parent">Ouderlijk toezicht</Text>
	<Text name="msgshare_info_level">Niveau %1</Text>
	<Text name="msgshare_info_space">Vrije ruimte</Text>
	<Text name="msgshare_del_data_ask">De data zal worden verwijderd.
Weet u zeker dat u wilt doorgaan?</Text>
	<Text name="msgshare_deleted">Het verwijderen is voltooid.</Text>
	<Text name="msgshare_error_del">Het verwijderen is mislukt.</Text>
	<Text name="msgshare_error_del_ms_locked">Het verwijderen is mislukt.
De Memory Stick™ is vergrendeld.</Text>
	<Text name="msgshare_error_notplay_ms">Toegang tot de Memory Stick™ is niet mogelijk.</Text>
	<Text name="msgshare_error_notplay_em">Toegang tot de systeemopslag is niet mogelijk.</Text>
	<Text name="msgshare_error_no_data">Er is geen data beschikbaar.</Text>
	<Text name="msgshare_error_no_ms">Er is geen Memory Stick™ geplaatst.</Text>
	<Text name="msgshare_error_ms_full">Er is onvoldoende ruimte op de Memory Stick™.</Text>
	<Text name="msgshare_error_em_full">Er is niet voldoende vrije ruimte op de systeemopslag.</Text>
	<Text name="msgshare_error_ms_locked">De Memory Stick™ is vergrendeld.</Text>
	<Text name="msgshare_date_num">%1/%2/%3</Text>
	<Text name="msgshare_datetime_num">%1/%2/%3  %4:%5:%6</Text>
	<Text name="msgshare_datetime_num_ap">%1/%2/%3  %4:%5:%6 %7</Text>
	<Text name="msgshare_corrupted_data">Beschadigde data</Text>
	<Text name="msgshare_error_parental_lock">Beperkte inhoud</Text>
	<Text name="msgshare_error_parental_lock_data">Beperkte data</Text>
	<Text name="msgshare_sd_error_load_data_corrupted">Het laden is mislukt.
De data zijn beschadigd.</Text>
	<Text name="msgshare_sd_error_load_no_data">Het laden is mislukt.
Er zijn geen data beschikbaar.</Text>
	<Text name="msgshare_sd_error_save_ms_full">Het opslaan is mislukt.
Er is onvoldoende ruimte op de Memory Stick™.
Er is minstens %1 meer ruimte vereist.</Text>
	<Text name="msgshare_sd_error_save_em_full">Het opslaan is mislukt.
Er is niet voldoende vrije ruimte op de systeemopslag.
Er is minstens %1 meer ruimte vereist.</Text>
	<Text name="msgshare_sd_error_save_ms_locked">Het opslaan is mislukt.
De Memory Stick™ is vergrendeld.</Text>
	<Text name="msgshare_error_load">Laden is mislukt.</Text>
	<Text name="msgshare_error_save">Opslaan is mislukt.</Text>
	<Text name="msgshare_wait">Een ogenblik geduld...</Text>
	<Text name="msgshare_game">Game</Text>
	<Text name="msgshare_sd_error_save_data_corrupted">Het opslaan is mislukt.
De data zijn beschadigd.</Text>
	<Text name="msgshare_info_details">Details</Text>
	<Text name="msg_copying_em">Bezig met kopiëren naar de systeemopslag...
Een ogenblik geduld.</Text>
	<Text name="msg_copying_ms">Bezig met kopiëren naar de Memory Stick™...
Een ogenblik geduld.</Text>
	<Text name="msgsavedata_info_savedatatitle">Opgeslagen data</Text>
	<Text name="msgsavedata_cmn_load_ask">Wilt u deze data laden?</Text>
	<Text name="msgsavedata_cmn_loading">Bezig met laden...
Een ogenblik geduld.</Text>
	<Text name="msgsavedata_cmn_loaded">Het laden is voltooid.</Text>
	<Text name="msgsavedata_cmn_save_ask">Wilt u deze data opslaan?</Text>
	<Text name="msgsavedata_cmn_saving">Bezig met opslaan...
Een ogenblik geduld.</Text>
	<Text name="msgsavedata_cmn_saved">Het opslaan is voltooid.</Text>
	<Text name="msgsavedata_cmn_overwrite_ask">Wilt u de data overschrijven?</Text>
	<Text name="msgsavedata_cmn_save">Opslaan</Text>
	<Text name="msgsavedata_cmn_load">Laden</Text>
	<Text name="msgsavedata_cmn_new">Nieuw</Text>
	<Text name="msgsavedata_bu_start">U wordt gevraagd om de Memory Stick™ %1 keer te verwisselen.
Druk op de toets %e om te beginnen.</Text>
	<Text name="msgsavedata_bu_read_data">Bezig met lezen van de te kopiëren data... (%1/%2)
Verwijder de bron-Memory Stick™ niet.</Text>
	<Text name="msgsavedata_bu_insert_msto_ask">Plaats de doel-Memory Stick™ en druk op de toets %e.
(%1/%2)</Text>
	<Text name="msgsavedata_bu_saving">Bezig met kopiëren... (%1/%2)
Verwijder de Memory Stick™ niet.</Text>
	<Text name="msgsavedata_bu_insert_msfrom">Plaats de bron-Memory Stick™ en druk op de toets %e.
(%1/%2)</Text>
	<Text name="msgsavedata_bu_saved">Het kopiëren is voltooid.
Plaats de bron-Memory Stick™.</Text>
	<Text name="msgsavedata_bu_cancel_ask">Wilt u het kopiëren annuleren?</Text>
	<Text name="msgsavedata_bu_delete_incomplete">Als u de onvoltooide kopieerdata wilt verwijderen, plaatst u de doel-Memory Stick™ en drukt u op de toets %e.
Druk op de toets %b om te annuleren zonder te verwijderen.</Text>
	<Text name="msgsavedata_bu_deleted">Het verwijderen is voltooid.
Plaats de bron-Memory Stick™.</Text>
	<Text name="msgsavedata_bu_error_ms_removed">Het kopiëren is mislukt.
De Memory Stick™ is verwijderd.</Text>
	<Text name="msgsavedata_bu_error_ms_no_access">Het kopiëren is mislukt.
Er is geen toegang mogelijk tot de Memory Stick™.</Text>
	<Text name="msgsavedata_bu_error_ms_no_dest">Er is geen Memory Stick™ geplaatst.
Plaats de doel-Memory Stick™.</Text>
	<Text name="msgsavedata_bu_error_ms_no_source">Er is geen Memory Stick™ geplaatst.
Plaats de bron-Memory Stick™.</Text>
	<Text name="msgsavedata_bu_error_ms_wrong_dest">De Memory Stick™ is onjuist.
Plaats de doel-Memory Stick™.</Text>
	<Text name="msgsavedata_bu_error_ms_wrong_source">De Memory Stick™ is onjuist.
Plaats de bron-Memory Stick™.</Text>
	<Text name="msgsavedata_bu_error_ms_notread">Het kopiëren is mislukt.
De Memory Stick™ kan niet worden gelezen.</Text>
	<Text name="msgsavedata_opt_backup">Kopiëren</Text>
	<Text name="msgsavedata_error_corrupted_data_notcopied">Deze data kan niet worden gekopieerd.
De data zijn beschadigd.</Text>
	<Text name="msgsavedata_cmn_save_cancel_ask">Wilt u het opslaan annuleren?</Text>
	<Text name="msgsavedata_error_copy">Deze data kan niet worden gekopieerd.</Text>
	<Text name="msgsavedata_error_copy_ms_full">Het kopiëren is mislukt.
Er is onvoldoende ruimte op de Memory Stick™.</Text>
	<Text name="msg_saveddata_overwrite_conf">Er is al opgeslagen data met dezelfde naam.
Wilt u de bestaande data overschrijven?</Text>
	<Text name="msg_copied">Het kopiëren is voltooid.</Text>
	<Text name="msg_error_copy_failed">Het kopiëren is mislukt.</Text>
	<Text name="msgerror_load_ms_no_access">Het laden is mislukt.
Toegang tot de Memory Stick™ is niet mogelijk.</Text>
	<Text name="msgerror_load_em_no_access">Het laden is mislukt.
Toegang tot de systeemopslag is niet mogelijk.</Text>
	<Text name="msgerror_sd_error_load_ms_removed">Het laden is mislukt.
De Memory Stick™ is verwijderd.</Text>
	<Text name="msgerror_sd_error_save_ms_no_access">Het opslaan is mislukt.
Toegang tot de Memory Stick™ is niet mogelijk.</Text>
	<Text name="msgerror_sd_error_save_em_no_access">Het opslaan is mislukt.
Toegang tot de systeemopslag is niet mogelijk.</Text>
	<Text name="msgerror_sd_error_save_ms_removed">Het opslaan is mislukt.
De Memory Stick™ is verwijderd.</Text>
	<Text name="msgerror_error_del_ms_no_access">Het verwijderen is mislukt.
Toegang tot de Memory Stick™ is niet mogelijk.</Text>
	<Text name="msgerror_error_del_em_no_access">Het verwijderen is mislukt.
Toegang tot de systeemopslag is niet mogelijk.</Text>
	<Text name="msgerror_error_del_ms_removed">Het verwijderen is mislukt.
De Memory Stick™ is verwijderd.</Text>
	<Text name="msg_deleting">Bezig met verwijderen...
Een ogenblik geduld.</Text>
	<Text name="msg_error_ms_not_found">Plaats een Memory Stick™.</Text>
</TextLang>
