<?xml version="1.0" encoding="utf-8"?>
<!-- This XML was generated by Rcomage v1.1.1 -->
<TextLang>
	<Text name="msgshare_info_size">Tamanho</Text>
	<Text name="msgshare_info_title">Título</Text>
	<Text name="msgshare_info_none">-</Text>
	<Text name="msgshare_ctrlpnl_viewmode">Modo de Visão</Text>
	<Text name="msgshare_error_lan_off">Ocorreu um erro de ligação.
O interruptor WLAN, no sistema PSP™, não está ligado.</Text>
	<Text name="msgshare_error_wireless_off">Ocorreu um erro de ligação.
O interruptor WIRELESS (sem fios), no sistema PSP™, não está ligado.</Text>
	<Text name="msgshare_lang_japanese">Japonês</Text>
	<Text name="msgshare_lang_english">Inglês</Text>
	<Text name="msgshare_lang_french">Francês</Text>
	<Text name="msgshare_lang_spanish">Espanhol</Text>
	<Text name="msgshare_lang_german">Alemão</Text>
	<Text name="msgshare_lang_italian">Italiano</Text>
	<Text name="msgshare_lang_dutch">Holandês</Text>
	<Text name="msgshare_lang_portuguese">Português</Text>
	<Text name="msgshare_lang_danish">Dinamarquês</Text>
	<Text name="msgshare_lang_swedish">Sueco</Text>
	<Text name="msgshare_lang_finnish">Finlandês</Text>
	<Text name="msgshare_lang_norwegian">Norueguês</Text>
	<Text name="msgshare_lang_russian">Russo</Text>
	<Text name="msgshare_lang_korean">Coreano</Text>
	<Text name="msgshare_lang_chinese">Chinês</Text>
	<Text name="msgshare_lang_polish">Polaco</Text>
	<Text name="msgshare_error_connect">Ocorreu um erro de ligação.</Text>
	<Text name="msgshare_error">Ocorreu um erro.</Text>
	<Text name="msgshare_game">Jogo</Text>
	<Text name="msgshare_error_ap_disconnect">Ocorreu um erro de ligação.
Foi desligado do ponto de acesso.</Text>
	<Text name="msgshare_error_connection_timeout">A ligação ao servidor excedeu o tempo.</Text>
	<Text name="msg_hd">HD</Text>
	<Text name="msg_sd">SD</Text>
	<Text name="msgtop_video">Vídeo</Text>
	<Text name="msgnetconf_error_dhcp_com">Ocorreu um erro de ligação.
Houve um erro de comunicação DHCP.</Text>
	<Text name="msgmusic_info_genre">Género</Text>
	<Text name="msg_all">Todas</Text>
	<Text name="msg_error_invalid_account">Não é possível aceder a este conteúdo através da sua conta.</Text>
	<Text name="msgsystem_yes">Sim</Text>
	<Text name="msgsystem_no">Não</Text>
	<Text name="msgsystem_enter">Confirmar</Text>
	<Text name="msgsystem_back">Retroceder</Text>
	<Text name="msg_error_wrong_idpw">A ID de início de sessão (endereço de correio electrónico) ou a palavra-passe estão incorrectas.</Text>
	<Text name="msg_search">Pesquisa</Text>
	<Text name="msg_language">Idioma</Text>
	<Text name="msg_program_guide">Descrição</Text>
	<Text name="msg_book_comics">Comics</Text>
	<Text name="msg_author">Elenco</Text>
	<Text name="msg_pages">Páginas</Text>
	<Text name="msg_lang_chinese_t">Chinês tradicional</Text>
	<Text name="msg_lang_chinese_s">Chinês simplificado</Text>
	<Text name="msg_season_variable_psn">Temporada %1</Text>
	<Text name="msg_episode_variable_psn">Episódio %1</Text>
	<Text name="msg_minute">%1 minutos</Text>
	<Text name="msg_mmyyyy_jan">Jan %1</Text>
	<Text name="msg_mmyyyy_feb">Fev %1</Text>
	<Text name="msg_mmyyyy_mar">Mar %1</Text>
	<Text name="msg_mmyyyy_apr">Abr %1</Text>
	<Text name="msg_mmyyyy_may">Mai %1</Text>
	<Text name="msg_mmyyyy_jun">Jun %1</Text>
	<Text name="msg_mmyyyy_jul">Jul %1</Text>
	<Text name="msg_mmyyyy_aug">Ago %1</Text>
	<Text name="msg_mmyyyy_sep">Set %1</Text>
	<Text name="msg_mmyyyy_oct">Out %1</Text>
	<Text name="msg_mmyyyy_nov">Nov %1</Text>
	<Text name="msg_mmyyyy_dec">Dez %1</Text>
	<Text name="msg_error_cannot_purchase_parental_control">Não é possível comprar este conteúdo em virtude das restrições de controlo parental.</Text>
	<Text name="msg_error_service_maintenance">Este serviço está presentemente em manutenção.</Text>
	<Text name="msg_shopping_quit_ask">Deseja sair da PlayStation®Store?</Text>
	<Text name="msg_store_top_psn">Vitrine</Text>
	<Text name="msg_view_downloads_psn">Ver as transferências</Text>
	<Text name="msg_view_cart_psn">Visualizar o cesto</Text>
	<Text name="msg_add_to_cart_psn">Adicionar ao cesto</Text>
	<Text name="msg_rental_psn">Alugar</Text>
	<Text name="msg_free_psn">Grátis</Text>
	<Text name="msg_buy_now_psn">Comprar agora</Text>
	<Text name="msg_download_psn">Transferir</Text>
	<Text name="msg_confirm_psn">Confirmar</Text>
	<Text name="msg_cancel_psn">Cancelar</Text>
	<Text name="msg_remove_psn">Remover</Text>
	<Text name="msg_added_to_cart_psn">Este artigo foi adicionado ao seu cesto.</Text>
	<Text name="msg_delete_from_cart_psn">Remover do cesto</Text>
	<Text name="msg_get_now_psn">Obter agora</Text>
	<Text name="msg_play_time_psn">Duração</Text>
	<Text name="msg_release_year_psn">Lançado</Text>
	<Text name="msg_original_air_date_psn">Transmitido</Text>
	<Text name="msg_audio_language_psn">Áudio</Text>
	<Text name="msg_subtitle_language_psn">Legendas</Text>
	<Text name="msg_cast_psn">Elenco</Text>
	<Text name="msg_crew_psn">Equipa</Text>
	<Text name="msg_crew_director_bracket_psn">(Realizador)</Text>
	<Text name="msg_crew_producer_bracket_psn">(Produtor)</Text>
	<Text name="msg_crew_writer_bracket_psn">(Argumentista)</Text>
	<Text name="msg_rental_video_caution_psn">Este conteúdo está disponível por aluguer durante %1 dias. No entanto, o conteúdo pode apenas ser reproduzido durante %2 horas após a primeira reprodução.
Para obter mais informações, consulte os Termos de Serviço e o Acordo de Utilizador da PlayStation®Network.</Text>
	<Text name="msg_cart_psn">Cesto de compras</Text>
	<Text name="msg_add_funds_psn">Adicionar fundos</Text>
	<Text name="msg_wallet_psn">Carteira</Text>
	<Text name="msg_sub_total_psn">Subtotal</Text>
	<Text name="msg_tax_psn">Imposto</Text>
	<Text name="msg_total_purchase_price_psn">Preço total da aquisição</Text>
	<Text name="msg_amount_removed_from_master_account_psn">Esta quantia será extraída da  carteira da conta mestra.</Text>
	<Text name="msg_resulting_wallet_amount_psn">Saldo na carteira</Text>
	<Text name="msg_continue_browsing_psn">Continue a pesquisar</Text>
	<Text name="msg_proceed_checkout_psn">Prossiga para a finalização da compra</Text>
	<Text name="msg_cart_empty_psn">O seu cesto está actualmente vazio.</Text>
	<Text name="msg_aboutus_pp_tosua_psn">Sobre nós | Política de Privacidade | Termos de Serviço | Avisos de saúde</Text>
	<Text name="msg_no_content_found_psn">Nenhum conteúdo foi encontrado.</Text>
	<Text name="msg_crew_director_producer_psn">Realizador / Produtor</Text>
	<Text name="msg_crew_writer_psn">Argumentista</Text>
	<Text name="msg_error_cart_item_full_psn">O seu cesto está cheio. Impossível adicionar este artigo ao seu cesto.</Text>
	<Text name="msg_error_cart_value_full_check_pls_psn">O valor dos artigos no seu cesto excede o limite de uma única transacção.

Por favor, confirme os artigos da sua compra.</Text>
	<Text name="msg_error_cannot_select_content_psn">Impossível seleccionar este conteúdo neste momento.</Text>
	<Text name="msg_error_no_item_psn">Não existem itens que possa adquirir neste momento.</Text>
	<Text name="msg_exit_psn">Sair</Text>
	<Text name="msg_ok_psn">OK</Text>
	<Text name="msg_code_input_psn">Utilizar Códigos</Text>
	<Text name="msg_to_proceed_need_signup_ask">Para continuar, deve inscrever-se na PlayStation®Network.
Pretende inscrever-se agora?</Text>
	<Text name="msg_error_service_not_available_region_psn">Este serviço não se encontra disponível no seu país/região.</Text>
	<Text name="msg_rent_now_psn">Alugar</Text>
	<Text name="msg_purchase_psn">Adquirir</Text>
	<Text name="msg_quit2_ask">Pretende sair?</Text>
	<Text name="msg_register_system">Registar este sistema</Text>
	<Text name="msg_system_registered_scee">O registo deste sistema foi concluído.</Text>
	<Text name="msg_system_already_registered">Já foi registado um sistema PSP™go com esta conta.</Text>
	<Text name="msg_umdv_next_step_scee">Utiliza esta conta num sistema PSP™ compatível com Universal Media Discs para acederes à PlayStation®Store. Em seguida, regista a versão em Universal Media Disc de qualquer um dos jogos que possuas para transferires 3 jogos da categoria "Recompensas PSP™go".</Text>
	<Text name="msg_error_registered_another_account">Este sistema já foi registado com outra conta.</Text>
	<Text name="msg_insert_umd_to_register_scee">Insere um jogo em Universal Media Disc e escolhe 3 jogos para transferência.</Text>
	<Text name="msg_error_game_already_registered">Este jogo já está registado.</Text>
	<Text name="msg_error_game_cannot_register">Não é possível registar este jogo.</Text>
	<Text name="msg_error_no_umd">Não está introduzido nenhum disco.</Text>
	<Text name="msg_game_registered_scee">Registo concluído.
Utiliza uma PSP™go para acederes à PlayStation®Store e transfere o Tema PSP™go da categoria "Recompensas PSP™go".</Text>
	<Text name="msg_aspect_ratio_psn">Proporção</Text>
	<Text name="msg_widescreen_psn">Ecrã Panorâmico</Text>
	<Text name="msg_fullscreen_psn">Ecrã Inteiro</Text>
	<Text name="msg_remains_psn">Restante</Text>
	<Text name="msg_license_renewal_psn">Prolongar Data</Text>
	<Text name="msg_license_renewal_conf_psn">A data de expiração deste conteúdo será prolongada.
Pretende continuar?</Text>
	<Text name="msg_error_cannot_choose_pack_content_psn">Este conteúdo está incluído em [%1].
É necessário adquirir previamente o [%1].</Text>
	<Text name="msg_error_pack_expired_purchase_conf">Atingiu-se a data de expiração de [%1].
Deseja adquirir [%1] na PlayStation®Store?</Text>
	<Text name="msg_error_renew_pack_consumed">Não foi possível concluir a prorrogação da data de expiração.
Foi atingido o limite máximo de itens de conteúdo que podem ser utilizados durante este período.</Text>
	<Text name="msg_drawer_bracket_psn">(Artista)</Text>
	<Text name="msg_original_author_bracket_psn">(Autor)</Text>
	<Text name="msg_2ch_psn">2 canais</Text>
	<Text name="msg_5.1ch_psn">5.1 canais</Text>
	<Text name="msg_composer_supervisor_bracket_psn"></Text>
	<Text name="msg_translator_bracket_psn"></Text>
	<Text name="msg_magazine_psn"></Text>
	<Text name="msg_book_release_psn">Publicado</Text>
	<Text name="msg_account_information_required_psn">Para utilizar este serviço, deverá primeiro guardar as informações do seu cartão de crédito com a sua conta.
Pretende guardar as informações do seu cartão de crédito?</Text>
	<Text name="msg_error_cannot_use_service_this_account">Não é possível utilizar este serviço nesta conta.</Text>
	<Text name="msg_error_ban_suspend_psn_account">O acesso à PlayStation®Network através desta conta foi banido ou suspenso temporariamente.</Text>
	<Text name="msg_error_ban_suspend_psn_console">O acesso à PlayStation®Network a partir deste sistema foi banido ou suspenso temporariamente.</Text>
	<Text name="msg_operation_unavailable_visit_following_site">Esta operação não está disponível aqui.
Para mais detalhes, visite o seguinte Web site no seu computador:
http://pc.playstation.net/</Text>
</TextLang>
