<?xml version="1.0" encoding="utf-8"?>
<!-- This XML was generated by Rcomage v1.1.1 -->
<TextLang>
	<Text name="msgshare_umd">UMD™</Text>
	<Text name="msgshare_ms">Memory Stick™</Text>
	<Text name="msg_em">主机内存</Text>
	<Text name="msgshare_info_none">-</Text>
	<Text name="msgshare_percent">%1%%</Text>
	<Text name="msgshare_error_notplay_ms">无法存取Memory Stick™。</Text>
	<Text name="msgshare_error_notplay_em">无法存取主机内存。</Text>
	<Text name="msgshare_error_no_ms">没有插入Memory Stick™。</Text>
	<Text name="msgshare_error_ms_full">Memory Stick™上没有足够的空余容量。</Text>
	<Text name="msgshare_error_em_full">主机内存没有足够的空余容量。</Text>
	<Text name="msgshare_error_ms_locked">Memory Stick™被写保护。</Text>
	<Text name="msgshare_error_lan_off">发生了连接错误。
PSP™主机上的无线LAN开关没有开启。</Text>
	<Text name="msgshare_error_wireless_off">发生了连接错误。
PSP™主机上的WIRELESS（无线）开关没有开启。</Text>
	<Text name="msgshare_time_bar">--:--:--</Text>
	<Text name="msgshare_error_fatal">升级失败。
请拨打服务热线寻求技术支持。</Text>
	<Text name="msgshare_latest_ver">已经安装了最新的系统数据。
不需要进行升级。</Text>
	<Text name="msgshare_updateprompt_updateunnecessary">此PSP™的系统文件是版本%1。
不需要进行升级。</Text>
	<Text name="msgshare_error_connect_dns">无法连接到服务器。
发生了DNS错误。</Text>
	<Text name="msgshare_error_ap_disconnect">发生了连接错误。
与接入点间的连接被断开。</Text>
	<Text name="msgshare_checking">正在检测。
请稍等。</Text>
	<Text name="msg_error_display_output">如正处于影像输出至外部设备中，将不能操作这功能。
请切换影像的输出至PSP™。</Text>
	<Text name="msg_system_update">系统升级</Text>
	<Text name="msgnetconf_searching">正在检测。
请稍等。</Text>
	<Text name="msgupdate_new_found">通过网络升级发现了更新的版本。
插入包含%1MB以上空余容量的Memory Stick™后，按%e键进行下载。</Text>
	<Text name="msgupdate_downloading">正在下载。
请不要关闭主机电源或取出Memory Stick™。</Text>
	<Text name="msgupdate_downloading_em">正在下载。
请不要关闭主机电源。</Text>
	<Text name="msg_update_conf_game_resume_data">若执行升级，[继续游戏]的数据将被删除。
确定要继续吗？</Text>
	<Text name="msgupdate_downloaded_system_update"><![CDATA[下载完毕。
按%e键可以开始升级。
若要以后升级，请选择[设定] > [系统升级]的[从存储设备升级]。]]></Text>
	<Text name="msgupdate_error_start_no_memory">无法进行升级。
系统内存不足。</Text>
	<Text name="msgupdate_error_com_no_memory">无法与服务器进行通信。
系统内存不足。</Text>
	<Text name="msgupdate_error_connect">无法连接到服务器。</Text>
	<Text name="msgupdate_error_connect_proxyserver">无法连接到服务器。
无法与HTTP代理服务器建立连接。</Text>
	<Text name="msgupdate_error_download_ms_removed">无法下载。
Memory Stick™被取出。</Text>
	<Text name="msgupdate_error_download_ms_no_access">无法下载。
无法存取Memory Stick™。</Text>
	<Text name="msgupdate_error_download_em_no_access">无法下载。
无法存取主机内存。</Text>
	<Text name="msgupdate_error_download_no_memory">无法下载。
系统内存不足。</Text>
	<Text name="msgupdate_error_download_dns">无法下载。
发生了DNS错误。</Text>
	<Text name="msgupdate_error_download_proxyserver">无法下载。
无法与HTTP代理服务器建立连接。</Text>
	<Text name="msgupdate_error_download_cannot_connect">无法下载。
无法与服务器建立连接。</Text>
	<Text name="msgupdate_error_server_maintenance">服务器可能正在进行维护或升级。
请稍候再试。</Text>
	<Text name="msgupdate_error_start">无法升级。</Text>
	<Text name="msgupdate_error_start_ms_removed">无法升级。
Memory Stick™被取出。</Text>
	<Text name="msgupdate_error_download">无法下载。</Text>
	<Text name="msg_update_select">请选择升级方式。</Text>
	<Text name="msg_update_net">通过互联网升级</Text>
	<Text name="msg_update_media">从存储设备升级</Text>
	<Text name="msg_update_follow_found">检测到以下的升级数据。</Text>
	<Text name="msg_location">位置</Text>
	<Text name="msg_error_no_updatedata">未能检测到可使用的升级数据。</Text>
	<Text name="msgupdater_cancel_update_ask">要取消升级吗？</Text>
	<Text name="msg_version">版本</Text>
</TextLang>
