<?xml version="1.0" encoding="utf-8"?>
<!-- This XML was generated by Rcomage v1.1.1 -->
<TextLang>
	<Text name="msgshare_umd">UMD™</Text>
	<Text name="msgshare_ms">Memory Stick™</Text>
	<Text name="msg_em">System Storage</Text>
	<Text name="msgshare_info_none">-</Text>
	<Text name="msgshare_percent">%1%%</Text>
	<Text name="msgshare_error_notplay_ms">The Memory Stick™ could not be accessed.</Text>
	<Text name="msgshare_error_notplay_em">The system storage could not be accessed.</Text>
	<Text name="msgshare_error_no_ms">There is no Memory Stick™ inserted.</Text>
	<Text name="msgshare_error_ms_full">There is not enough free space on the Memory Stick™.</Text>
	<Text name="msgshare_error_em_full">There is not enough free space in the system storage.</Text>
	<Text name="msgshare_error_ms_locked">The Memory Stick™ is locked.</Text>
	<Text name="msgshare_error_lan_off">A connection error has occurred.
The WLAN switch on the PSP™ system is not turned on.</Text>
	<Text name="msgshare_error_wireless_off">A connection error has occurred.
The WIRELESS switch on the PSP™ system is not turned on.</Text>
	<Text name="msgshare_time_bar">--:--:--</Text>
	<Text name="msgshare_error_fatal">The update failed.
Contact technical support for assistance.</Text>
	<Text name="msgshare_latest_ver">The latest version of the system software is already installed.
There is no need to update.</Text>
	<Text name="msgshare_updateprompt_updateunnecessary">The system software of your PSP™ system is version %1.
There is no need to update.</Text>
	<Text name="msgshare_error_connect_dns">Connection to the server failed.
A DNS error has occurred.</Text>
	<Text name="msgshare_error_ap_disconnect">A connection error has occurred.
You have been disconnected from the access point.</Text>
	<Text name="msgshare_checking">Checking...
Please wait.</Text>
	<Text name="msg_error_display_output">You cannot use this feature when displaying video output on a connected device.
Switch to display video output on the PSP™ system.</Text>
	<Text name="msg_system_update">System Update</Text>
	<Text name="msgnetconf_searching">Scanning...
Please wait.</Text>
	<Text name="msgupdate_new_found">Network Update has found a later version.
To download, insert a Memory Stick™ with at least %1 MB free space and press the %e button.</Text>
	<Text name="msgupdate_downloading">Downloading...
Do not turn off the power or remove the Memory Stick™.</Text>
	<Text name="msgupdate_downloading_em">Downloading...
Do not turn off the power.</Text>
	<Text name="msg_update_conf_game_resume_data">If you perform the update, the data for [Resume Game] will be deleted.
Are you sure you want to continue?</Text>
	<Text name="msgupdate_downloaded_system_update"><![CDATA[Download completed.
Press the %e button to start the update.
To install later, go to [Settings] > [System Update] and select [Update via Storage Media].]]></Text>
	<Text name="msgupdate_error_start_no_memory">The update cannot be started.
System memory is low.</Text>
	<Text name="msgupdate_error_com_no_memory">Communication with the server failed.
System memory is low.</Text>
	<Text name="msgupdate_error_connect">A connection to the server could not be established.</Text>
	<Text name="msgupdate_error_connect_proxyserver">Connection to the server failed.
A connection to the HTTP proxy server could not be established.</Text>
	<Text name="msgupdate_error_download_ms_removed">The download failed.
The Memory Stick™ has been removed.</Text>
	<Text name="msgupdate_error_download_ms_no_access">The download failed.
The Memory Stick™ could not be accessed.</Text>
	<Text name="msgupdate_error_download_em_no_access">The download failed.
The system storage could not be accessed.</Text>
	<Text name="msgupdate_error_download_no_memory">The download failed.
System memory is low.</Text>
	<Text name="msgupdate_error_download_dns">The download failed.
A DNS error has occurred.</Text>
	<Text name="msgupdate_error_download_proxyserver">The download failed.
A connection to the HTTP proxy server could not be established.</Text>
	<Text name="msgupdate_error_download_cannot_connect">The download failed.
A connection to the server could not be established.</Text>
	<Text name="msgupdate_error_server_maintenance">Currently, the server may be down for maintenance or updating.
Please try again later.</Text>
	<Text name="msgupdate_error_start">The update could not be started.</Text>
	<Text name="msgupdate_error_start_ms_removed">The update could not be started.
The Memory Stick™ has been removed.</Text>
	<Text name="msgupdate_error_download">The download failed.</Text>
	<Text name="msg_update_select">Select an update method.</Text>
	<Text name="msg_update_net">Update via Internet</Text>
	<Text name="msg_update_media">Update via Storage Media</Text>
	<Text name="msg_update_follow_found">The following update data was found:</Text>
	<Text name="msg_location">Location</Text>
	<Text name="msg_error_no_updatedata">No applicable update data was found.</Text>
	<Text name="msgupdater_cancel_update_ask">Do you want to cancel the update?</Text>
	<Text name="msg_version">Version</Text>
</TextLang>
